yzy/__init__.py
yzy/arxiv.py
yzy/checkv.py
yzy/conf_list.txt
yzy/file2md.py
yzy/id2md.py
yzy-0.1.3.dist-info/LICENSE
yzy-0.1.3.dist-info/METADATA
yzy-0.1.3.dist-info/WHEEL
yzy-0.1.3.dist-info/top_level.txt
yzy-0.1.3.dist-info/RECORD
