Metadata-Version: 2.1
Name: yzy
Version: 0.1.3
Summary: Utils
Author-email: Zhiyuan Yang <im.crazyang@gmail.com>
Project-URL: Homepage, https://github.com/yzy1996/Python-Code/tree/master/Python%2BarXiv
Project-URL: Bug Tracker, https://github.com/yzy1996/Python-Code/issues
Classifier: Programming Language :: Python :: 3
Classifier: License :: OSI Approved :: MIT License
Classifier: Operating System :: OS Independent
Requires-Python: >=3.8
License-File: LICENSE
Requires-Dist: feedparser
Requires-Dist: pypdf
